LICENSE
MANIFEST.in
README.rst
setup.py
cooper/__init__.py
cooper/cooper.py
cooper.egg-info/PKG-INFO
cooper.egg-info/SOURCES.txt
cooper.egg-info/dependency_links.txt
cooper.egg-info/top_level.txt