Metadata-Version: 1.1
Name: cooper
Version: 0.1.3
Summary: Easy and safe cooperative methods
Home-page: https://github.com/arximboldi/cooper
Author: Juan Pedro Bolívar Puente
Author-email: raskolnikov@gnu.org
License: UNKNOWN
Download-URL: https://github.com/arximboldi/cooper/tarball/0.1.3
Platform: UNKNOWN
